LICENSE
apipe/__init__.py
apipe/_cached.py
apipe/_dask.py
apipe-0.1.9.dist-info/LICENSE
apipe-0.1.9.dist-info/METADATA
apipe-0.1.9.dist-info/WHEEL
apipe-0.1.9.dist-info/RECORD
