Metadata-Version: 2.1
Name: apipe
Version: 0.1.9
Summary: Data pipelines with lazy computation and caching
Home-page: https://github.com/mysterious-ben/apipe
License: Apache License, Version 2.0
Keywords: python,pipeline,dask,pandas
Author: Mysterious Ben
Author-email: datascience@tuta.io
Requires-Python: >=3.9,<4.0
Classifier: License :: Other/Proprietary License
Classifier: Programming Language :: Python :: 3
Classifier: Programming Language :: Python :: 3.9
Classifier: Programming Language :: Python :: 3.10
Classifier: Programming Language :: Python :: 3.11
Classifier: Programming Language :: Python :: 3.12
Requires-Dist: cloudpickle (>=2)
Requires-Dist: dask[delayed] (>=2023)
Requires-Dist: loguru (>=0.5)
Requires-Dist: numpy (>=1.25,<2.0)
Requires-Dist: pandas[pyarrow] (>=2.1,<3.0)
Requires-Dist: xxhash (>=3.4,<4.0)
Project-URL: Repository, https://github.com/mysterious-ben/apipe
